[
  { "key": "aae", "value": "aae全球专递" },
  { "key": "anjie", "value": "安捷快递" },
  { "key": "anxindakuaixi", "value": "安信达快递" },
  { "key": "biaojikuaidi", "value": "彪记快递" },
  { "key": "bht", "value": "bht" },
  { "key": "baifudongfang", "value": "百福东方国际物流" },
  { "key": "coe", "value": "中国东方（COE）" },
  { "key": "changyuwuliu", "value": "长宇物流" },
  { "key": "datianwuliu", "value": "大田物流" },
  { "key": "debangwuliu", "value": "德邦物流" },
  { "key": "dhl", "value": "dhl" },
  { "key": "dpex", "value": "dpex" },
  { "key": "dsukuaidi", "value": "d速快递" },
  { "key": "disifang", "value": "递四方" },
  { "key": "ems", "value": "ems快递" },
  { "key": "fedex", "value": "fedex（国外）" },
  { "key": "feikangda", "value": "飞康达物流" },
  { "key": "fenghuangkuaidi", "value": "凤凰快递" },
  { "key": "feikuaida", "value": "飞快达" },
  { "key": "guotongkuaidi", "value": "国通快递" },
  { "key": "ganzhongnengda", "value": "港中能达物流" },
  { "key": "guangdongyouzhengwuliu", "value": "广东邮政物流" },
  { "key": "gongsuda", "value": "共速达" },
  { "key": "huitongkuaidi", "value": "汇通快运" },
  { "key": "hengluwuliu", "value": "恒路物流" },
  { "key": "huaxialongwuliu", "value": "华夏龙物流" },
  { "key": "haihongwangsong", "value": "海红" },
  { "key": "haiwaihuanqiu", "value": "海外环球" },
  { "key": "jiayiwuliu", "value": "佳怡物流" },
  { "key": "jinguangsudikuaijian", "value": "京广速递" },
  { "key": "jixianda", "value": "急先达" },
  { "key": "jjwl", "value": "佳吉物流" },
  { "key": "jymwl", "value": "加运美物流" },
  { "key": "jindawuliu", "value": "金大物流" },
  { "key": "jialidatong", "value": "嘉里大通" },
  { "key": "jykd", "value": "晋越快递" },
  { "key": "kuaijiesudi", "value": "快捷速递" },
  { "key": "lianb", "value": "联邦快递（国内）" },
  { "key": "lianhaowuliu", "value": "联昊通物流" },
  { "key": "longbanwuliu", "value": "龙邦物流" },
  { "key": "lijisong", "value": "立即送" },
  { "key": "lejiedi", "value": "乐捷递" },
  { "key": "minghangkuaidi", "value": "民航快递" },
  { "key": "meiguokuaidi", "value": "美国快递" },
  { "key": "menduimen", "value": "门对门" },
  { "key": "ocs", "value": "OCS" },
  { "key": "peisihuoyunkuaidi", "value": "配思货运" },
  { "key": "quanchenkuaidi", "value": "全晨快递" },
  { "key": "quanfengkuaidi", "value": "全峰快递" },
  { "key": "quanjitong", "value": "全际通物流" },
  { "key": "quanritongkuaidi", "value": "全日通快递" },
  { "key": "quanyikuaidi", "value": "全一快递" },
  { "key": "rufengda", "value": "如风达" },
  { "key": "santaisudi", "value": "三态速递" },
  { "key": "shenghuiwuliu", "value": "盛辉物流" },
  { "key": "shentong", "value": "申通" },
  { "key": "shunfeng", "value": "顺丰" },
  { "key": "sue", "value": "速尔物流" },
  { "key": "shengfeng", "value": "盛丰物流" },
  { "key": "saiaodi", "value": "赛澳递" },
  { "key": "tiandihuayu", "value": "天地华宇" },
  { "key": "tiantian", "value": "天天快递" },
  { "key": "tnt", "value": "tnt" },
  { "key": "ups", "value": "ups" },
  { "key": "wanjiawuliu", "value": "万家物流" },
  { "key": "wenjiesudi", "value": "文捷航空速递" },
  { "key": "wuyuan", "value": "伍圆" },
  { "key": "wxwl", "value": "万象物流" },
  { "key": "xinbangwuliu", "value": "新邦物流" },
  { "key": "xinfengwuliu", "value": "信丰物流" },
  { "key": "yafengsudi", "value": "亚风速递" },
  { "key": "yibangwuliu", "value": "一邦速递" },
  { "key": "youshuwuliu", "value": "优速物流" },
  { "key": "youzhengguonei", "value": "邮政包裹挂号信" },
  { "key": "youzhengguoji", "value": "邮政国际包裹挂号信" },
  { "key": "yuanchengwuliu", "value": "远成物流" },
  { "key": "yuantong", "value": "圆通速递" },
  { "key": "yuanweifeng", "value": "源伟丰快递" },
  { "key": "yuanzhijiecheng", "value": "元智捷诚快递" },
  { "key": "yunda", "value": "韵达快运" },
  { "key": "yuntongkuaidi", "value": "运通快递" },
  { "key": "yuefengwuliu", "value": "越丰物流" },
  { "key": "yad", "value": "源安达" },
  { "key": "yinjiesudi", "value": "银捷速递" },
  { "key": "zhaijisong", "value": "宅急送" },
  { "key": "zhongtiekuaiyun", "value": "中铁快运" },
  { "key": "zhongtong", "value": "中通速递" },
  { "key": "zhongyouwuliu", "value": "中邮物流" },
  { "key": "zhongxinda", "value": "忠信达" },
  { "key": "zhimakaimen", "value": "芝麻开门" }
]
